rvtools/__init__.py
rvtools/construct/__init__.py
rvtools/construct/_helpers.py
rvtools/construct/beta.py
rvtools/construct/lognorm.py
rvtools/construct/loguniform.py
rvtools/construct/norm.py
rvtools/construct/pert.py
rvtools/construct/tp_uniform.py
rvtools/construct/uniform.py
rvtools/dists/__init__.py
rvtools/dists/gen/__init__.py
rvtools/dists/gen/certainty.py
rvtools/dists/gen/halves_uniform.py
rvtools/dists/gen/tp_uniform.py
rvtools/fam.py
rvtools-0.1.6.dist-info/METADATA
rvtools-0.1.6.dist-info/WHEEL
rvtools-0.1.6.dist-info/RECORD
