Metadata-Version: 2.1
Name: rvtools
Version: 0.1.6
Summary: Top-level package for Probability distribution and random variable tools.
Home-page: https://github.com/tadamcz/rvtools
Author: Tom Adamczewski
Author-email: tadamczewskipublic@gmail.com
Requires-Python: >=3.9,<3.13
Classifier: Natural Language :: English
Classifier: Programming Language :: Python :: 3
Classifier: Programming Language :: Python :: 3.9
Classifier: Programming Language :: Python :: 3.10
Classifier: Programming Language :: Python :: 3.11
Requires-Dist: betapert (>=0.1.4,<0.2.0)
Requires-Dist: copula-wrapper (>=0.1.3,<0.2.0)
